{"system":{"id":"eed3d451-4ff5-4193-b951-ffcc68954299","rev":"7ab6211","version":"2.33.1","date":"2020-02-11T21:08:32.838"},"organisationUnitLevels":[{"lastUpdated":"2015-08-09T12:58:05.001","level":3,"created":"2011-12-24T12:24:22.935","name":"Chiefdom","id":"tTUf91fCytl","translations":[]},{"lastUpdated":"2015-08-09T12:58:04.997","level":2,"created":"2011-12-24T12:24:22.935","name":"District","id":"wjP19dkFeIk","translations":[]},{"lastUpdated":"2015-08-09T12:58:05.005","level":4,"created":"2011-12-24T12:24:22.935","name":"Facility","id":"m9lBJogzE95","translations":[]},{"lastUpdated":"2015-08-09T12:58:05.003","level":1,"created":"2011-12-24T12:24:22.935","name":"National","id":"H1KlN4QIauv","translations":[]}]}